protonUI/__init__.py
protonUI/core/__init__.py
protonUI/core/element.py
protonUI/core/engine.py
protonUI/core/input.py
protonUI/core/shader.py
protonUI/ui/__init__.py
protonUI/ui/window.py
protonUI-0.0.2.dist-info/LICENCE
protonUI-0.0.2.dist-info/METADATA
protonUI-0.0.2.dist-info/WHEEL
protonUI-0.0.2.dist-info/top_level.txt
protonUI-0.0.2.dist-info/RECORD
